pyavreceiver/__init__.py
pyavreceiver/command.py
pyavreceiver/const.py
pyavreceiver/dispatch.py
pyavreceiver/error.py
pyavreceiver/functions.py
pyavreceiver/http_api.py
pyavreceiver/http_connection.py
pyavreceiver/priority_queue.py
pyavreceiver/receiver.py
pyavreceiver/response.py
pyavreceiver/telnet_connection.py
pyavreceiver/zone.py
pyavreceiver/arcam/__init__.py
pyavreceiver/denon/__init__.py
pyavreceiver/denon/commands.py
pyavreceiver/denon/commands.yaml
pyavreceiver/denon/const.py
pyavreceiver/denon/error.py
pyavreceiver/denon/http_api.py
pyavreceiver/denon/http_connection.py
pyavreceiver/denon/parse.py
pyavreceiver/denon/receiver.py
pyavreceiver/denon/response.py
pyavreceiver/denon/telnet_connection.py
pyavreceiver/denon/zone.py
pyavreceiver/emotiva/__init__.py
pyavreceiver/examples/__init__.py
pyavreceiver/examples/test_connect.py
pyavreceiver/onkyo/__init__.py
pyavreceiver/sony/__init__.py
pyavreceiver/template/__init__.py
pyavreceiver/template/commands.py
pyavreceiver/template/const.py
pyavreceiver/template/error.py
pyavreceiver/template/http_api.py
pyavreceiver/template/receiver.py
pyavreceiver/template/response.py
pyavreceiver/template/zone.py
pyavreceiver/yamaha/__init__.py
pyavreceiver-0.0.10.dist-info/LICENSE
pyavreceiver-0.0.10.dist-info/METADATA
pyavreceiver-0.0.10.dist-info/WHEEL
pyavreceiver-0.0.10.dist-info/top_level.txt
pyavreceiver-0.0.10.dist-info/RECORD
